image_downloader/Exceptions.py
image_downloader/__init__.py
image_downloader/downloader.py
light_picture_downloader-0.0.1.dist-info/LICENSE
light_picture_downloader-0.0.1.dist-info/METADATA
light_picture_downloader-0.0.1.dist-info/WHEEL
light_picture_downloader-0.0.1.dist-info/top_level.txt
light_picture_downloader-0.0.1.dist-info/RECORD
